LICENSE
README.md
setup.py
huangiu_scraper.egg-info/PKG-INFO
huangiu_scraper.egg-info/SOURCES.txt
huangiu_scraper.egg-info/dependency_links.txt
huangiu_scraper.egg-info/requires.txt
huangiu_scraper.egg-info/top_level.txt
pypi_scraper/__init__.py